{
    "@class": "com.kony.gen.viz.model.container.KVizSegment2",
    "DNDConfig": null,
    "__parentReadjusting__": false,
    "_bounces_": false,
    "_data_": [
        {
            "lblCheck": {
                "@class": "com.viz.ide.model.segment.SimpleTextSegmentData",
                "text": ""
            },
            "lblValue": {
                "@class": "com.viz.ide.model.segment.SimpleTextSegmentData",
                "text": ""
            }
        }
    ],
    "_height_": {
        "type": "string",
        "value": "94%"
    },
    "_indicator_": "none",
    "_left_": {
        "type": "string",
        "value": "0dp"
    },
    "_margin_": [
        0,
        0,
        0,
        0
    ],
    "_orientation_": 2,
    "_padding_": [
        0,
        0,
        0,
        0
    ],
    "_top_": {
        "type": "string",
        "value": "6%"
    },
    "_width_": {
        "type": "string",
        "value": "100%"
    },
    "autogrowmode": 0,
    "canUpdateUI": true,
    "centerx": {
        "type": "string",
        "value": "50%"
    },
    "containerweight": 100,
    "counter": "00",
    "focusedindex": null,
    "focuseditem": null,
    "groupcells": false,
    "hasSections": false,
    "id": "segCrewSearchResults",
    "ide_onReachingEnd": "AS_Segment_af5e01ab40d64d8ea6aa54b4f5ff3918",
    "ide_onRowClick": "AS_Segment_f75d3dff33764b7daf459fb19f3ad2ca",
    "info": null,
    "ipad": {
        "psp": {
            "indicator": "rowselect"
        }
    },
    "iphone": {
        "psp": {
            "bounces": false,
            "indicator": "none"
        }
    },
    "iscustomlayout": false,
    "isvisible": true,
    "kuid": "f0adbcf4b8684a75b495f9993746df8c",
    "masterdata": {},
    "name": "kony.ui.SegmentedUI2",
    "needpageindicator": true,
    "pageoffdotimage": "pageoffdot.png",
    "pageondotimage": "pageondot.png",
    "paginationconfig": {
        "position": "bottom"
    },
    "parent": "flxSegContainer",
    "pf": "frmAddCrew",
    "retaincontentalignment": false,
    "retainflexpositionproperties": false,
    "retainselection": false,
    "rowTemplateId": "c6bf13e8481d4c59a1ff5d170362dade",
    "rowcounter": 0,
    "rowfocusskin": "s60bf3bc0dee4a6792513210706a387b",
    "rowskin": "s81d7be59b9248f194765e1fe6485675",
    "rowtemplate": "flxTempFilters",
    "screenlevelwidget": false,
    "seccounter": 0,
    "sectionHeaderTemplateId": null,
    "sectionheaderskin": "sb8127d4ed124d5286cfb7034f037297",
    "selectedRows": null,
    "selectedState": false,
    "selectedindex": null,
    "selectedindices": null,
    "selecteditems": null,
    "selectedsectionindex": 0,
    "selectionbehavior": "default",
    "separatorcolor": "ffffff00",
    "separatorrequired": true,
    "separatorthickness": 0,
    "showscrollbars": false,
    "viewtype": "tableview",
    "vizProps": {},
    "wType": "Segment",
    "widgetalignment": 5,
    "widgetdatamap": {
        "flxCheckContainer": "flxCheckContainer",
        "flxLine": "flxLine",
        "flxOrgSearchBox": "flxOrgSearchBox",
        "flxTempFilters": "flxTempFilters",
        "flxcheck": "flxcheck",
        "lblCheck": "lblCheck",
        "lblValue": "lblValue"
    },
    "zindex": 1
}