{
    "DNDConfig": null,
    "__parentReadjusting__": false,
    "_height_": {
        "type": "string",
        "value": "100%"
    },
    "_left_": {
        "type": "string",
        "value": "0"
    },
    "_margin_": [
        0,
        0,
        0,
        0
    ],
    "_orientation_": 6,
    "_padding_": [
        0,
        0,
        0,
        0
    ],
    "_percent_": true,
    "_skin_": "sad115ab4b9c44459ce4adc827bb1122",
    "_top_": {
        "type": "string",
        "value": "0"
    },
    "_width_": {
        "type": "string",
        "value": "35%"
    },
    "allboxes": [],
    "autogrowmode": 0,
    "canUpdateUI": true,
    "children": [
        "CopylblNormalHours0baf68aa4af9342",
        "CopylbCountryAsterisk0df2fc0e17af64d"
    ],
    "clipbounds": true,
    "containerweight": 100,
    "enablescrolling": true,
    "id": "CopyflxActivityBox0g846109d133844",
    "info": null,
    "iscustomlayout": false,
    "isvisible": true,
    "kuid": "g5b4d0906fe546beaeb98aa4eb532e6e",
    "layouttype": 3,
    "name": "kony.ui.FlexContainer",
    "parent": "flxAssetSubType1",
    "pf": "frmAddDPR",
    "retaincontentalignment": false,
    "retainflexpositionproperties": false,
    "retainflowhorizontalalignment": false,
    "snapgridsize": 10,
    "snaptogrid": true,
    "wType": "FlexContainer",
    "widgetalignment": 1
}