{
    "AS_FlexContainer_j46187fc48634abb97184c8566989810": {
        "id": "AS_FlexContainer_j46187fc48634abb97184c8566989810",
        "type": "ACTION_SEQUENCE",
        "params": [{
            "datatype": "collection",
            "name": "eventobject"
        }],
        "contextObj": {
            "type": "forms",
            "platform": "",
            "KUID": "gdfecfbb2e0a408ea1aabdb3a4b63a91",
            "name": "frmNewLogin"
        },
        "language": "js",
        "actions": [{
            "id": "ADD_SNIPPET__e8754b21341b49e6b59c4fed33df0523",
            "type": "ADD_SNIPPET",
            "codeSnippet": "this.isAuthUsingTouchSupported();",
            "parentId": null,
            "callbackType": null
        }]
    }
}